<?xml version="1.0" encoding="UTF-8" standalone="yes"?>
<ExtractVariables async="false" continueOnError="true" enabled="true" name="BillUser-extract-query-param">
    <DisplayName>BillUser Extract Query Param</DisplayName>
    <Source>request</Source>
    <IgnoreUnresolvedVariables>true</IgnoreUnresolvedVariables>
<QueryParam name="ns:eBayAuthToken">
<Pattern ignoreCase="true">{ns:eBayAuthToken}</Pattern>
</QueryParam>
<QueryParam name="ns:HardExpirationWarning">
<Pattern ignoreCase="true">{ns:HardExpirationWarning}</Pattern>
</QueryParam>
<QueryParam name="ns:AppId">
<Pattern ignoreCase="true">{ns:AppId}</Pattern>
</QueryParam>
<QueryParam name="ns:DevId">
<Pattern ignoreCase="true">{ns:DevId}</Pattern>
</QueryParam>
<QueryParam name="ns:AuthCert">
<Pattern ignoreCase="true">{ns:AuthCert}</Pattern>
</QueryParam>
<QueryParam name="ns:Username">
<Pattern ignoreCase="true">{ns:Username}</Pattern>
</QueryParam>
<QueryParam name="ns:Password">
<Pattern ignoreCase="true">{ns:Password}</Pattern>
</QueryParam>
<QueryParam name="ns:Signature">
<Pattern ignoreCase="true">{ns:Signature}</Pattern>
</QueryParam>
<QueryParam name="ns:Subject">
<Pattern ignoreCase="true">{ns:Subject}</Pattern>
</QueryParam>
<QueryParam name="ns:AuthToken">
<Pattern ignoreCase="true">{ns:AuthToken}</Pattern>
</QueryParam>
<QueryParam name="ns:DetailLevel">
<Pattern ignoreCase="true">{ns:DetailLevel}</Pattern>
</QueryParam>
<QueryParam name="ns:ErrorLanguage">
<Pattern ignoreCase="true">{ns:ErrorLanguage}</Pattern>
</QueryParam>
<QueryParam name="ns:Version">
<Pattern ignoreCase="true">{ns:Version}</Pattern>
</QueryParam>
<QueryParam name="ns:Amount">
<Pattern ignoreCase="true">{ns:Amount}</Pattern>
</QueryParam>
<QueryParam name="ns:currencyID">
<Pattern ignoreCase="true">{ns:currencyID}</Pattern>
</QueryParam>
<QueryParam name="ns:MpID">
<Pattern ignoreCase="true">{ns:MpID}</Pattern>
</QueryParam>
<QueryParam name="ns:PaymentType">
<Pattern ignoreCase="true">{ns:PaymentType}</Pattern>
</QueryParam>
<QueryParam name="ns:Memo">
<Pattern ignoreCase="true">{ns:Memo}</Pattern>
</QueryParam>
<QueryParam name="ns:EmailSubject">
<Pattern ignoreCase="true">{ns:EmailSubject}</Pattern>
</QueryParam>
<QueryParam name="ns:Tax">
<Pattern ignoreCase="true">{ns:Tax}</Pattern>
</QueryParam>
<QueryParam name="ns:currencyID">
<Pattern ignoreCase="true">{ns:currencyID}</Pattern>
</QueryParam>
<QueryParam name="ns:Shipping">
<Pattern ignoreCase="true">{ns:Shipping}</Pattern>
</QueryParam>
<QueryParam name="ns:currencyID">
<Pattern ignoreCase="true">{ns:currencyID}</Pattern>
</QueryParam>
<QueryParam name="ns:Handling">
<Pattern ignoreCase="true">{ns:Handling}</Pattern>
</QueryParam>
<QueryParam name="ns:currencyID">
<Pattern ignoreCase="true">{ns:currencyID}</Pattern>
</QueryParam>
<QueryParam name="ns:ItemName">
<Pattern ignoreCase="true">{ns:ItemName}</Pattern>
</QueryParam>
<QueryParam name="ns:ItemNumber">
<Pattern ignoreCase="true">{ns:ItemNumber}</Pattern>
</QueryParam>
<QueryParam name="ns:Invoice">
<Pattern ignoreCase="true">{ns:Invoice}</Pattern>
</QueryParam>
<QueryParam name="ns:Custom">
<Pattern ignoreCase="true">{ns:Custom}</Pattern>
</QueryParam>
<QueryParam name="ns:ButtonSource">
<Pattern ignoreCase="true">{ns:ButtonSource}</Pattern>
</QueryParam>
<QueryParam name="ns:SoftDescriptor">
<Pattern ignoreCase="true">{ns:SoftDescriptor}</Pattern>
</QueryParam>
<QueryParam name="ns:ReturnFMFDetails">
<Pattern ignoreCase="true">{ns:ReturnFMFDetails}</Pattern>
</QueryParam>
</ExtractVariables>
